krippendorff_graph.py
krippendorff_graph-0.1.4.dist-info/licenses/LICENSE
krippendorff_graph-0.1.4.dist-info/METADATA
krippendorff_graph-0.1.4.dist-info/WHEEL
krippendorff_graph-0.1.4.dist-info/top_level.txt
krippendorff_graph-0.1.4.dist-info/RECORD
