Metadata-Version: 2.4
Name: krippendorff-graph
Version: 0.1.4
Summary: A Python package for computing krippendorffs alpha for graph (modified from https://github.com/grrrr/krippendorff-alpha/blob/master/krippendorff_alpha.py)
Home-page: https://anonymous.4open.science/r/BE2B/
Author: anonymous author
Author-email: anonymous@email.com
License: Apache 2 License
License-File: LICENSE
Requires-Dist: pandas
Requires-Dist: scikit-learn
Requires-Dist: requests
Requires-Dist: networkx
Requires-Dist: tqdm
Requires-Dist: numpy
Dynamic: author
Dynamic: author-email
Dynamic: description
Dynamic: description-content-type
Dynamic: home-page
Dynamic: license
Dynamic: license-file
Dynamic: requires-dist
Dynamic: summary
